pokepy/__init__.py
pokepy/api.py
pokepy/resources_v2.py
pokepy/fcache/__init__.py
pokepy/fcache/cache.py
pokepy/fcache/posixemulation.py
pokepy-0.6.2.dist-info/LICENSE
pokepy-0.6.2.dist-info/METADATA
pokepy-0.6.2.dist-info/WHEEL
pokepy-0.6.2.dist-info/top_level.txt
pokepy-0.6.2.dist-info/RECORD
