Metadata-Version: 2.1
Name: pokepy
Version: 0.6.2
Summary: A Python wrapper for PokéAPI (https://pokeapi.co)
Home-page: https://github.com/PokeAPI/pokepy
Author: Paul Hallett
Author-email: hello@phalt.co
License: BSD
Project-URL: Documentation, https://pokeapi.github.io/pokepy/
Keywords: pokepy PokéAPI
Platform: UNKNOWN
Classifier: Development Status :: 4 - Beta
Classifier: Intended Audience :: Developers
Classifier: License :: OSI Approved :: BSD License
Classifier: Natural Language :: English
Classifier: Programming Language :: Python :: 2
Classifier: Programming Language :: Python :: 2.7
Classifier: Programming Language :: Python :: 3
Classifier: Programming Language :: Python :: 3.4
Classifier: Programming Language :: Python :: 3.5
Classifier: Programming Language :: Python :: 3.6
Classifier: Programming Language :: Python :: 3.7
Classifier: Programming Language :: Python :: 3.8
